{
  "minecraft:recipes/building_blocks/black_stained_glass": {
    "criteria": {
      "has_glass": "2025-01-10 14:12:36 -0300"
    },
    "done": true
  },
  "immersiveengineering:recipes/immersiveengineering/crafting/capacitor_lv": {
    "criteria": {
      "has_lead_ingot": "2025-01-09 19:12:39 -0300"
    },
    "done": true
  },
  "securitycraft:recipes/securitycraft/reinforced_purple_stained_glass_pane_from_dye": {
    "criteria": {
      "has_glass": "2025-01-10 14:12:36 -0300"
    },
    "done": true
  },
  "minecraft:recipes/redstone/lever": {
    "criteria": {
      "has_cobblestone": "2025-01-09 20:08:46 -0300"
    },
    "done": true
  },
  "minecraft:recipes/building_blocks/cobblestone_stairs_from_cobblestone_stonecutting": {
    "criteria": {
      "has_cobblestone": "2025-01-09 20:08:46 -0300"
    },
    "done": true
  },
  "create:recipes/create.palettes/horizontal_framed_glass_from_glass_colorless_stonecutting": {
    "criteria": {
      "has_glass_colorless": "2025-01-10 14:12:36 -0300"
    },
    "done": true
  },
  "ae2wtlib:recipes/infinity_booster_card": {
    "criteria": {
      "has_wit": "2025-01-08 19:15:19 -0300",
      "has_wpt": "2025-01-08 19:15:19 -0300",
      "has_wct": "2025-01-08 19:15:19 -0300"
    },
    "done": true
  },
  "naturescompass:natures_compass": {
    "criteria": {
      "has_compass": "2025-01-08 19:15:19 -0300"
    },
    "done": true
  },
  "tconstruct:tools/materials_and_you": {
    "criteria": {
      "crafted_book": "2025-01-08 19:15:24 -0300"
    },
    "done": true
  },
  "securitycraft:recipes/securitycraft/reinforced_andesite_with_vanilla_diorite": {
    "criteria": {
      "has_cobblestone": "2025-01-09 20:08:46 -0300"
    },
    "done": true
  },
  "tconstruct:internal/starting_book": {
    "criteria": {
      "tick": "2025-01-08 19:15:24 -0300"
    },
    "done": true
  },
  "securitycraft:recipes/securitycraft/reinforced_green_stained_glass_pane_from_dye": {
    "criteria": {
      "has_glass": "2025-01-10 14:12:36 -0300"
    },
    "done": true
  },
  "minecraft:recipes/building_blocks/chiseled_stone_bricks": {
    "criteria": {
      "has_tag": "2025-01-10 14:08:30 -0300"
    },
    "done": true
  },
  "minecraft:recipes/building_blocks/stone_brick_slab_from_stone_bricks_stonecutting": {
    "criteria": {
      "has_stone_bricks": "2025-01-10 14:08:30 -0300"
    },
    "done": true
  },
  "minecraft:recipes/building_blocks/gray_stained_glass": {
    "criteria": {
      "has_glass": "2025-01-10 14:12:36 -0300"
    },
    "done": true
  },
  "ae2wtlib:recipes/magnet_card": {
    "criteria": {
      "has_wct": "2025-01-08 19:15:19 -0300"
    },
    "done": true
  },
  "immersiveengineering:recipes/immersiveengineering/crafting/plate_lead_hammering": {
    "criteria": {
      "has_lead_ingot": "2025-01-09 19:12:39 -0300"
    },
    "done": true
  },
  "securitycraft:recipes/securitycraft/block_pocket_manager": {
    "criteria": {
      "has_redstone_block": "2025-01-09 20:07:25 -0300"
    },
    "done": true
  },
  "minecraft:recipes/redstone/redstone": {
    "criteria": {
      "has_redstone_block": "2025-01-09 20:07:25 -0300"
    },
    "done": true
  },
  "create:recipes/create.base/crafting/kinetics/nozzle": {
    "criteria": {
      "has_item": "2025-01-09 20:07:40 -0300"
    },
    "done": true
  },
  "minecraft:recipes/building_blocks/purple_stained_glass": {
    "criteria": {
      "has_glass": "2025-01-10 14:12:36 -0300"
    },
    "done": true
  },
  "securitycraft:recipes/securitycraft/reinforced_green_stained_glass": {
    "criteria": {
      "has_glass": "2025-01-10 14:12:36 -0300"
    },
    "done": true
  },
  "securitycraft:recipes/securitycraft/reinforced_red_stained_glass_pane_from_dye": {
    "criteria": {
      "has_glass": "2025-01-10 14:12:36 -0300"
    },
    "done": true
  },
  "iceandfire:iceandfire/root": {
    "criteria": {
      "tick": "2025-01-08 19:15:24 -0300"
    },
    "done": true
  },
  "securitycraft:recipes/securitycraft/reinforced_light_blue_stained_glass_pane_from_dye": {
    "criteria": {
      "has_glass": "2025-01-10 14:12:36 -0300"
    },
    "done": true
  },
  "minecraft:recipes/decorations/chest": {
    "criteria": {
      "has_lots_of_items": "2025-01-08 19:50:11 -0300"
    },
    "done": true
  },
  "securitycraft:recipes/securitycraft/reinforced_red_stained_glass_pane_from_glass": {
    "criteria": {
      "has_glass": "2025-01-10 14:12:36 -0300"
    },
    "done": true
  },
  "secretroomsmod:recipes/secretroomsmod/camouflage_paste": {
    "criteria": {
      "has_earth_item": "2025-01-24 10:36:40 -0300"
    },
    "done": true
  },
  "travelersbackpack:recipes/travelersbackpack/wolf": {
    "criteria": {
      "has_bone": "2025-01-09 19:13:08 -0300"
    },
    "done": true
  },
  "securitycraft:recipes/securitycraft/reinforced_black_stained_glass_pane_from_dye": {
    "criteria": {
      "has_glass": "2025-01-10 14:12:36 -0300"
    },
    "done": true
  },
  "securitycraft:recipes/securitycraft/reinforced_orange_stained_glass": {
    "criteria": {
      "has_glass": "2025-01-10 14:12:36 -0300"
    },
    "done": true
  },
  "minecraft:recipes/decorations/black_carpet_from_white_carpet": {
    "criteria": {
      "has_white_carpet": "2025-01-09 19:57:08 -0300"
    },
    "done": true
  },
  "minecraft:recipes/decorations/purple_carpet_from_white_carpet": {
    "criteria": {
      "has_white_carpet": "2025-01-09 19:57:08 -0300"
    },
    "done": true
  },
  "minecraft:recipes/building_blocks/blue_stained_glass": {
    "criteria": {
      "has_glass": "2025-01-10 14:12:36 -0300"
    },
    "done": true
  },
  "minecraft:recipes/decorations/red_carpet_from_white_carpet": {
    "criteria": {
      "has_white_carpet": "2025-01-09 19:57:08 -0300"
    },
    "done": true
  },
  "securitycraft:recipes/securitycraft/reinforced_orange_stained_glass_pane_from_glass": {
    "criteria": {
      "has_glass": "2025-01-10 14:12:36 -0300"
    },
    "done": true
  },
  "botania:recipes/botania/turntable": {
    "criteria": {
      "has_alt_item": "2025-01-08 19:50:11 -0300"
    },
    "done": true
  },
  "minecraft:recipes/transportation/spruce_boat": {
    "criteria": {
      "in_water": "2025-01-09 19:15:51 -0300"
    },
    "done": true
  },
  "bigreactors:recipes/bigreactors.turbine/turbine/reinforced/activetap_fe": {
    "criteria": {
      "has_item2": "2025-01-09 20:07:25 -0300"
    },
    "done": true
  },
  "securitycraft:recipes/securitycraft/reinforced_light_blue_stained_glass": {
    "criteria": {
      "has_glass": "2025-01-10 14:12:36 -0300"
    },
    "done": true
  },
  "minecraft:recipes/building_blocks/cracked_stone_bricks": {
    "criteria": {
      "has_stone_bricks": "2025-01-10 14:08:30 -0300"
    },
    "done": true
  },
  "minecraft:recipes/redstone/dispenser": {
    "criteria": {
      "has_bow": "2025-01-08 19:50:11 -0300"
    },
    "done": true
  },
  "botania:recipes/botania/animated_torch": {
    "criteria": {
      "has_item": "2025-01-09 20:06:59 -0300"
    },
    "done": true
  },
  "projecte:recipes/projecte/low_covalence_dust": {
    "criteria": {
      "has_cobble": "2025-01-09 20:08:46 -0300"
    },
    "done": true
  },
  "securitycraft:recipes/securitycraft/reinforced_blue_stained_glass_pane_from_dye": {
    "criteria": {
      "has_glass": "2025-01-10 14:12:36 -0300"
    },
    "done": true
  },
  "minecraft:recipes/building_blocks/emerald_block": {
    "criteria": {
      "has_emerald": "2025-01-08 19:58:34 -0300"
    },
    "done": true
  },
  "bigreactors:recipes/bigreactors.reactor/reactor/reinforced/passivefluidport_forge": {
    "criteria": {
      "has_item2": "2025-01-08 19:50:11 -0300"
    },
    "done": true
  },
  "securitycraft:recipes/securitycraft/reinforced_andesite_with_vanilla_cobblestone": {
    "criteria": {
      "has_cobblestone": "2025-01-09 20:08:46 -0300"
    },
    "done": true
  },
  "travelersbackpack:recipes/travelersbackpack/emerald": {
    "criteria": {
      "has_emerald": "2025-01-08 19:58:34 -0300"
    },
    "done": true
  },
  "create:recipes/create.palettes/vertical_framed_glass_from_glass_colorless_stonecutting": {
    "criteria": {
      "has_glass_colorless": "2025-01-10 14:12:36 -0300"
    },
    "done": true
  },
  "bigreactors:recipes/bigreactors.reactor/reactor/basic/activetap_fe": {
    "criteria": {
      "has_item2": "2025-01-09 20:07:25 -0300"
    },
    "done": true
  },
  "minecraft:recipes/building_blocks/cobblestone_slab": {
    "criteria": {
      "has_cobblestone": "2025-01-09 20:08:46 -0300"
    },
    "done": true
  },
  "securitycraft:recipes/securitycraft/reinforced_light_gray_stained_glass": {
    "criteria": {
      "has_glass": "2025-01-10 14:12:36 -0300"
    },
    "done": true
  },
  "minecraft:recipes/building_blocks/cobblestone_stairs": {
    "criteria": {
      "has_cobblestone": "2025-01-09 20:08:46 -0300"
    },
    "done": true
  },
  "securitycraft:recipes/securitycraft/reinforced_white_stained_glass_pane_from_glass": {
    "criteria": {
      "has_glass": "2025-01-10 14:12:36 -0300"
    },
    "done": true
  },
  "tconstruct:recipes/brewing/common/glass/vanilla/glass_bottle": {
    "criteria": {
      "has_glass": "2025-01-10 14:12:36 -0300"
    },
    "done": true
  },
  "securitycraft:recipes/securitycraft/secret_jungle_sign_item": {
    "criteria": {
      "has_sign": "2025-01-09 20:09:00 -0300"
    },
    "done": true
  },
  "minecraft:recipes/building_blocks/stone_brick_stairs_from_stone_bricks_stonecutting": {
    "criteria": {
      "has_stone_bricks": "2025-01-10 14:08:30 -0300"
    },
    "done": true
  },
  "industrialforegoing:recipes/industrialforegoing_core/plastic": {
    "criteria": {
      "has_plastic": "2025-01-08 19:15:19 -0300"
    },
    "done": true
  },
  "securitycraft:recipes/securitycraft/reinforced_light_blue_stained_glass_pane_from_glass": {
    "criteria": {
      "has_glass": "2025-01-10 14:12:36 -0300"
    },
    "done": true
  },
  "vanillatweaks:crafting_pad": {
    "criteria": {
      "has_pad": "2025-01-08 19:15:19 -0300"
    },
    "done": true
  },
  "immersiveengineering:recipes/immersiveengineering/crafting/capacitor_mv": {
    "criteria": {
      "has_nickel_ingot": "2025-01-09 19:12:41 -0300"
    },
    "done": true
  },
  "ae2wtlib:recipes/wireless_universal_terminal/upgrade_crafting": {
    "criteria": {
      "has_wct": "2025-01-08 19:15:19 -0300"
    },
    "done": true
  },
  "chiselsandbits:chiselsandbits/root": {
    "criteria": {
      "chisel": "2025-01-08 20:01:41 -0300"
    },
    "done": true
  },
  "create:recipes/create.base/crafting/kinetics/vertical_gearbox": {
    "criteria": {
      "has_item": "2025-01-09 20:03:53 -0300"
    },
    "done": true
  },
  "ae2wtlib:recipes/wireless_universal_terminal/ae": {
    "criteria": {
      "has_wit": "2025-01-08 19:15:19 -0300",
      "has_wpt": "2025-01-08 19:15:19 -0300"
    },
    "done": true
  },
  "naturescompass:natures_compass_sapling": {
    "criteria": {
      "has_recipe": "2025-01-08 19:15:19 -0300"
    },
    "done": true
  },
  "securitycraft:recipes/securitycraft/secret_spruce_sign_item": {
    "criteria": {
      "has_sign": "2025-01-09 20:09:00 -0300"
    },
    "done": true
  },
  "constructionwand:recipes/tools/stone_wand": {
    "criteria": {
      "has_item": "2025-01-09 20:08:46 -0300"
    },
    "done": true
  },
  "securitycraft:recipes/securitycraft/reinforced_red_stained_glass": {
    "criteria": {
      "has_glass": "2025-01-10 14:12:36 -0300"
    },
    "done": true
  },
  "immersiveengineering:recipes/immersiveengineering/crafting/plate_nickel_hammering": {
    "criteria": {
      "has_nickel_ingot": "2025-01-09 19:12:41 -0300"
    },
    "done": true
  },
  "securitycraft:recipes/securitycraft/reinforced_lime_stained_glass": {
    "criteria": {
      "has_glass": "2025-01-10 14:12:36 -0300"
    },
    "done": true
  },
  "mowziesmobs:kill_naga": {
    "criteria": {
      "naga": "2025-01-09 19:21:56 -0300"
    },
    "done": true
  },
  "chiselsandbits:recipes/chiselsandbits/wrench": {
    "criteria": {
      "has_b": "2025-01-08 19:59:56 -0300"
    },
    "done": true
  },
  "securitycraft:recipes/securitycraft/reinforced_blue_stained_glass_pane_from_glass": {
    "criteria": {
      "has_glass": "2025-01-10 14:12:36 -0300"
    },
    "done": true
  },
  "bigreactors:recipes/bigreactors.turbine/turbine/reinforced/passivefluidport_forge": {
    "criteria": {
      "has_item2": "2025-01-08 19:50:11 -0300"
    },
    "done": true
  },
  "minecraft:recipes/building_blocks/yellow_stained_glass": {
    "criteria": {
      "has_glass": "2025-01-10 14:12:36 -0300"
    },
    "done": true
  },
  "securitycraft:recipes/securitycraft/reinforced_white_stained_glass_pane_from_dye": {
    "criteria": {
      "has_glass": "2025-01-10 14:12:36 -0300"
    },
    "done": true
  },
  "travelersbackpack:recipes/travelersbackpack/skeleton": {
    "criteria": {
      "has_arrow": "2025-01-08 19:50:11 -0300"
    },
    "done": true
  },
  "vanillatweaks:pedestal": {
    "criteria": {
      "has_stone_bricks": "2025-01-10 14:08:30 -0300"
    },
    "done": true
  },
  "minecraft:story/mine_stone": {
    "criteria": {
      "get_stone": "2025-01-09 20:08:46 -0300"
    },
    "done": true
  },
  "minecraft:recipes/decorations/cyan_carpet_from_white_carpet": {
    "criteria": {
      "has_white_carpet": "2025-01-09 19:57:08 -0300"
    },
    "done": true
  },
  "securitycraft:recipes/securitycraft/reinforced_green_stained_glass_pane_from_glass": {
    "criteria": {
      "has_glass": "2025-01-10 14:12:36 -0300"
    },
    "done": true
  },
  "minecraft:recipes/decorations/furnace": {
    "criteria": {
      "has_cobblestone": "2025-01-09 20:08:46 -0300"
    },
    "done": true
  },
  "bigreactors:recipes/bigreactors.turbine/turbine/basic/passivefluidport_forge": {
    "criteria": {
      "has_item2": "2025-01-08 19:50:11 -0300"
    },
    "done": true
  },
  "minecraft:recipes/brewing/cauldron": {
    "criteria": {
      "has_water_bucket": "2025-01-08 19:50:11 -0300"
    },
    "done": true
  },
  "securitycraft:recipes/securitycraft/reinforced_gray_stained_glass_pane_from_glass": {
    "criteria": {
      "has_glass": "2025-01-10 14:12:36 -0300"
    },
    "done": true
  },
  "minecraft:recipes/building_blocks/red_stained_glass": {
    "criteria": {
      "has_glass": "2025-01-10 14:12:36 -0300"
    },
    "done": true
  },
  "minecraft:story/lava_bucket": {
    "criteria": {
      "lava_bucket": "2025-01-09 20:09:09 -0300"
    },
    "done": true
  },
  "minecraft:recipes/building_blocks/cobblestone_slab_from_cobblestone_stonecutting": {
    "criteria": {
      "has_cobblestone": "2025-01-09 20:08:46 -0300"
    },
    "done": true
  },
  "securitycraft:recipes/securitycraft/reinforced_gray_stained_glass_pane_from_dye": {
    "criteria": {
      "has_glass": "2025-01-10 14:12:36 -0300"
    },
    "done": true
  },
  "minecraft:recipes/building_blocks/stone_brick_slab": {
    "criteria": {
      "has_stone_bricks": "2025-01-10 14:08:30 -0300"
    },
    "done": true
  },
  "minecraft:recipes/transportation/birch_boat": {
    "criteria": {
      "in_water": "2025-01-09 19:15:51 -0300"
    },
    "done": true
  },
  "securitycraft:recipes/securitycraft/reinforced_purple_stained_glass_pane_from_glass": {
    "criteria": {
      "has_glass": "2025-01-10 14:12:36 -0300"
    },
    "done": true
  },
  "securitycraft:recipes/securitycraft/reinforced_brown_stained_glass_pane_from_dye": {
    "criteria": {
      "has_glass": "2025-01-10 14:12:36 -0300"
    },
    "done": true
  },
  "immersiveengineering:recipes/immersiveengineering/crafting/wire_lead": {
    "criteria": {
      "has_lead_ingot": "2025-01-09 19:12:39 -0300"
    },
    "done": true
  },
  "minecraft:recipes/transportation/acacia_boat": {
    "criteria": {
      "in_water": "2025-01-09 19:15:51 -0300"
    },
    "done": true
  },
  "create:shifting_gears": {
    "criteria": {
      "0": "2025-01-09 20:03:58 -0300"
    },
    "done": true
  },
  "minecraft:recipes/decorations/light_blue_carpet_from_white_carpet": {
    "criteria": {
      "has_white_carpet": "2025-01-09 19:57:08 -0300"
    },
    "done": true
  },
  "minecraft:recipes/building_blocks/orange_stained_glass": {
    "criteria": {
      "has_glass": "2025-01-10 14:12:36 -0300"
    },
    "done": true
  },
  "minecraft:adventure/root": {
    "criteria": {
      "killed_something": "2025-01-08 19:55:31 -0300"
    },
    "done": true
  },
  "securitycraft:recipes/securitycraft/reinforced_magenta_stained_glass_pane_from_glass": {
    "criteria": {
      "has_glass": "2025-01-10 14:12:36 -0300"
    },
    "done": true
  },
  "bigreactors:recipes/bigreactors.general/reprocessor/wasteinjector": {
    "criteria": {
      "has_item2": "2025-01-08 19:50:11 -0300"
    },
    "done": true
  },
  "immersiveengineering:recipes/immersiveengineering/crafting/plate_silver_hammering": {
    "criteria": {
      "has_silver_ingot": "2025-01-09 19:12:19 -0300"
    },
    "done": true
  },
  "chiselsandbits:recipes/chiselsandbits/modification_table": {
    "criteria": {
      "has_c": "2025-01-08 20:01:41 -0300"
    },
    "done": true
  },
  "minecraft:recipes/tools/stone_hoe": {
    "criteria": {
      "has_cobblestone": "2025-01-09 20:08:46 -0300"
    },
    "done": true
  },
  "securitycraft:recipes/securitycraft/reinforced_yellow_stained_glass": {
    "criteria": {
      "has_glass": "2025-01-10 14:12:36 -0300"
    },
    "done": true
  },
  "minecraft:adventure/kill_all_mobs": {
    "criteria": {
      "minecraft:skeleton": "2025-01-08 19:55:31 -0300",
      "minecraft:spider": "2025-01-09 19:56:12 -0300",
      "minecraft:zombie": "2025-01-09 19:56:15 -0300"
    },
    "done": false
  },
  "minecraft:recipes/decorations/stone_brick_wall": {
    "criteria": {
      "has_stone_bricks": "2025-01-10 14:08:30 -0300"
    },
    "done": true
  },
  "create:encased_fan": {
    "criteria": {
      "0": "2025-01-09 20:07:44 -0300"
    },
    "done": true
  },
  "minecraft:recipes/building_blocks/lime_stained_glass": {
    "criteria": {
      "has_glass": "2025-01-10 14:12:36 -0300"
    },
    "done": true
  },
  "minecraft:recipes/decorations/magenta_carpet_from_white_carpet": {
    "criteria": {
      "has_white_carpet": "2025-01-09 19:57:08 -0300"
    },
    "done": true
  },
  "minecraft:recipes/decorations/lime_carpet_from_white_carpet": {
    "criteria": {
      "has_white_carpet": "2025-01-09 19:57:08 -0300"
    },
    "done": true
  },
  "securitycraft:recipes/securitycraft/reinforced_cyan_stained_glass_pane_from_dye": {
    "criteria": {
      "has_glass": "2025-01-10 14:12:36 -0300"
    },
    "done": true
  },
  "minecraft:recipes/decorations/glass_pane": {
    "criteria": {
      "has_glass": "2025-01-10 14:12:36 -0300"
    },
    "done": true
  },
  "create:root": {
    "criteria": {
      "0": "2025-01-08 19:15:19 -0300"
    },
    "done": true
  },
  "chiselsandbits:recipes/chiselsandbits/chiseled_printer": {
    "criteria": {
      "has_c": "2025-01-08 20:01:41 -0300"
    },
    "done": true
  },
  "naturescompass:natures_compass_log": {
    "criteria": {
      "has_recipe": "2025-01-08 19:15:19 -0300"
    },
    "done": true
  },
  "create:recipes/create.base/crafting/kinetics/gearboxfrom_conversion": {
    "criteria": {
      "has_item": "2025-01-09 20:06:19 -0300"
    },
    "done": true
  },
  "minecraft:recipes/building_blocks/magenta_stained_glass": {
    "criteria": {
      "has_glass": "2025-01-10 14:12:36 -0300"
    },
    "done": true
  },
  "securitycraft:recipes/securitycraft/reinforced_dispenser": {
    "criteria": {
      "has_bow": "2025-01-08 19:50:11 -0300"
    },
    "done": true
  },
  "minecraft:recipes/decorations/green_carpet_from_white_carpet": {
    "criteria": {
      "has_white_carpet": "2025-01-09 19:57:08 -0300"
    },
    "done": true
  },
  "minecraft:recipes/decorations/snow": {
    "criteria": {
      "has_snowball": "2025-01-08 19:18:09 -0300"
    },
    "done": true
  },
  "minecraft:recipes/transportation/oak_boat": {
    "criteria": {
      "in_water": "2025-01-09 19:15:51 -0300"
    },
    "done": true
  },
  "securitycraft:recipes/securitycraft/reinforced_light_gray_stained_glass_pane_from_glass": {
    "criteria": {
      "has_glass": "2025-01-10 14:12:36 -0300"
    },
    "done": true
  },
  "securitycraft:recipes/securitycraft/reinforced_yellow_stained_glass_pane_from_glass": {
    "criteria": {
      "has_glass": "2025-01-10 14:12:36 -0300"
    },
    "done": true
  },
  "minecraft:recipes/building_blocks/light_blue_stained_glass": {
    "criteria": {
      "has_glass": "2025-01-10 14:12:36 -0300"
    },
    "done": true
  },
  "securitycraft:recipes/securitycraft/secret_dark_oak_sign_item": {
    "criteria": {
      "has_sign": "2025-01-09 20:09:00 -0300"
    },
    "done": true
  },
  "chiselsandbits:recipes/chiselsandbits/bit_bag": {
    "criteria": {
      "has_b": "2025-01-08 19:59:56 -0300"
    },
    "done": true
  },
  "minecraft:recipes/decorations/light_gray_carpet_from_white_carpet": {
    "criteria": {
      "has_white_carpet": "2025-01-09 19:57:08 -0300"
    },
    "done": true
  },
  "securitycraft:recipes/securitycraft/secret_crimson_sign_item": {
    "criteria": {
      "has_sign": "2025-01-09 20:09:00 -0300"
    },
    "done": true
  },
  "minecraft:recipes/building_blocks/stone_brick_stairs": {
    "criteria": {
      "has_stone_bricks": "2025-01-10 14:08:30 -0300"
    },
    "done": true
  },
  "securitycraft:recipes/securitycraft/reinforced_gray_stained_glass": {
    "criteria": {
      "has_glass": "2025-01-10 14:12:36 -0300"
    },
    "done": true
  },
  "immersiveengineering:recipes/immersiveengineering/crafting/radiator": {
    "criteria": {
      "has_water_bucket": "2025-01-08 19:50:11 -0300"
    },
    "done": true
  },
  "securitycraft:recipes/securitycraft/secret_warped_sign_item": {
    "criteria": {
      "has_sign": "2025-01-09 20:09:00 -0300"
    },
    "done": true
  },
  "securitycraft:recipes/securitycraft/reinforced_cyan_stained_glass": {
    "criteria": {
      "has_glass": "2025-01-10 14:12:36 -0300"
    },
    "done": true
  },
  "darkutils:adventure/faster_than_lightning": {
    "criteria": {
      "get_plate": "2025-01-10 14:04:56 -0300"
    },
    "done": true
  },
  "twilightforest:alt/compat/ie_shaders": {
    "criteria": {
      "ie_masterwork": "2025-01-08 19:15:19 -0300",
      "ie_uncommon": "2025-01-08 19:15:19 -0300",
      "tf_masterwork": "2025-01-08 19:15:19 -0300",
      "tf_uncommon": "2025-01-08 19:15:19 -0300",
      "tf_common": "2025-01-08 19:15:19 -0300",
      "ie_rare": "2025-01-08 19:15:19 -0300",
      "ie_shader": "2025-01-08 19:15:19 -0300",
      "ie_common": "2025-01-08 19:15:19 -0300",
      "ie_twilight": "2025-01-08 19:15:19 -0300",
      "tf_epic": "2025-01-08 19:15:19 -0300",
      "ie_epic": "2025-01-08 19:15:19 -0300",
      "tf_twilight": "2025-01-08 19:15:19 -0300",
      "tf_shader": "2025-01-08 19:15:19 -0300",
      "tf_rare": "2025-01-08 19:15:19 -0300"
    },
    "done": true
  },
  "create:recipes/create.base/crafting/kinetics/gearbox": {
    "criteria": {
      "has_item": "2025-01-09 20:03:53 -0300"
    },
    "done": true
  },
  "botania:recipes/botania/mana_detector": {
    "criteria": {
      "has_item": "2025-01-09 19:52:44 -0300"
    },
    "done": true
  },
  "minecraft:recipes/decorations/stone_brick_wall_from_stone_bricks_stonecutting": {
    "criteria": {
      "has_stone_bricks": "2025-01-10 14:08:30 -0300"
    },
    "done": true
  },
  "minecraft:recipes/brewing/glass_bottle": {
    "criteria": {
      "has_glass": "2025-01-10 14:12:36 -0300"
    },
    "done": true
  },
  "botania:recipes/botania/mana_fluxfield": {
    "criteria": {
      "has_item": "2025-01-09 20:07:25 -0300"
    },
    "done": true
  },
  "bigreactors:recipes/bigreactors.general/turbine/insanite_block": {
    "criteria": {
      "has_item": "2025-01-08 19:15:19 -0300"
    },
    "done": true
  },
  "minecraft:recipes/building_blocks/chiseled_stone_bricks_from_stone_bricks_stonecutting": {
    "criteria": {
      "has_stone_bricks": "2025-01-10 14:08:30 -0300"
    },
    "done": true
  },
  "securitycraft:recipes/securitycraft/reinforced_glass_pane": {
    "criteria": {
      "has_glass": "2025-01-10 14:12:36 -0300"
    },
    "done": true
  },
  "securitycraft:recipes/securitycraft/reinforced_brown_stained_glass_pane_from_glass": {
    "criteria": {
      "has_glass": "2025-01-10 14:12:36 -0300"
    },
    "done": true
  },
  "minecraft:recipes/building_blocks/white_stained_glass": {
    "criteria": {
      "has_glass": "2025-01-10 14:12:36 -0300"
    },
    "done": true
  },
  "create:recipes/create.palettes/framed_glass_from_glass_colorless_stonecutting": {
    "criteria": {
      "has_glass_colorless": "2025-01-10 14:12:36 -0300"
    },
    "done": true
  },
  "securitycraft:recipes/securitycraft/reinforced_black_stained_glass_pane_from_glass": {
    "criteria": {
      "has_glass": "2025-01-10 14:12:36 -0300"
    },
    "done": true
  },
  "bloodmagic:recipes/bloodmagictab/sacrificial_dagger": {
    "criteria": {
      "has_glass": "2025-01-10 14:12:36 -0300"
    },
    "done": true
  },
  "bigreactors:recipes/bigreactors.turbine/turbine/basic/activetap_fe": {
    "criteria": {
      "has_item2": "2025-01-09 20:07:25 -0300"
    },
    "done": true
  },
  "moguns:crayfish/root": {
    "criteria": {
      "tick": "2025-01-08 19:15:24 -0300"
    },
    "done": true
  },
  "mowziesmobs:root": {
    "criteria": {
      "custom_test_name": "2025-01-08 19:15:24 -0300"
    },
    "done": true
  },
  "securitycraft:recipes/securitycraft/reinforced_yellow_stained_glass_pane_from_dye": {
    "criteria": {
      "has_glass": "2025-01-10 14:12:36 -0300"
    },
    "done": true
  },
  "minecraft:recipes/building_blocks/green_stained_glass": {
    "criteria": {
      "has_glass": "2025-01-10 14:12:36 -0300"
    },
    "done": true
  },
  "minecraft:recipes/tools/stone_shovel": {
    "criteria": {
      "has_cobblestone": "2025-01-09 20:08:46 -0300"
    },
    "done": true
  },
  "minecraft:recipes/building_blocks/cyan_stained_glass": {
    "criteria": {
      "has_glass": "2025-01-10 14:12:36 -0300"
    },
    "done": true
  },
  "cataclysm:root": {
    "criteria": {
      "custom_test_name": "2025-01-08 19:15:24 -0300"
    },
    "done": true
  },
  "securitycraft:recipes/securitycraft/reinforced_andesite": {
    "criteria": {
      "has_cobblestone": "2025-01-09 20:08:46 -0300"
    },
    "done": true
  },
  "ae2wtlib:recipes/wireless_pattern_access_terminal": {
    "criteria": {
      "has_wt": "2025-01-08 19:15:19 -0300"
    },
    "done": true
  },
  "ae2wtlib:recipes/wireless_universal_terminal/upgrade_pattern_access": {
    "criteria": {
      "has_wit": "2025-01-08 19:15:19 -0300"
    },
    "done": true
  },
  "securitycraft:recipes/securitycraft/reinforced_black_stained_glass": {
    "criteria": {
      "has_glass": "2025-01-10 14:12:36 -0300"
    },
    "done": true
  },
  "minecraft:recipes/decorations/brown_carpet_from_white_carpet": {
    "criteria": {
      "has_white_carpet": "2025-01-09 19:57:08 -0300"
    },
    "done": true
  },
  "minecraft:recipes/misc/bone_meal": {
    "criteria": {
      "has_bone": "2025-01-09 19:13:08 -0300"
    },
    "done": true
  },
  "secretroomsmod:recipes/secretroomsmod/torch_lever": {
    "criteria": {
      "has_torch_lever": "2025-01-08 19:50:11 -0300"
    },
    "done": true
  },
  "securitycraft:recipes/securitycraft/laser_block": {
    "criteria": {
      "has_stone": "2025-01-09 20:08:46 -0300"
    },
    "done": true
  },
  "minecraft:recipes/decorations/orange_carpet_from_white_carpet": {
    "criteria": {
      "has_white_carpet": "2025-01-09 19:57:08 -0300"
    },
    "done": true
  },
  "chiselsandbits:recipes/chiselsandbits/bit_storage": {
    "criteria": {
      "has_c": "2025-01-08 20:01:41 -0300"
    },
    "done": true
  },
  "bigreactors:recipes/bigreactors.turbine/turbine/reinforced/activefluidport_forge": {
    "criteria": {
      "has_item2": "2025-01-09 20:09:09 -0300"
    },
    "done": true
  },
  "inventorypets:root": {
    "criteria": {
      "auto": "2025-01-08 19:15:19 -0300"
    },
    "done": true
  },
  "travelersbackpack:recipes/travelersbackpack/snow": {
    "criteria": {
      "has_snowball": "2025-01-08 19:18:09 -0300"
    },
    "done": true
  },
  "securitycraft:recipes/securitycraft/reinforced_blue_stained_glass": {
    "criteria": {
      "has_glass": "2025-01-10 14:12:36 -0300"
    },
    "done": true
  },
  "bigreactors:recipes/bigreactors.turbine/turbine/basic/activefluidport_forge": {
    "criteria": {
      "has_item2": "2025-01-09 20:09:09 -0300"
    },
    "done": true
  },
  "securitycraft:recipes/securitycraft/reinforced_diorite": {
    "criteria": {
      "has_cobblestone": "2025-01-09 20:08:46 -0300"
    },
    "done": true
  },
  "securitycraft:recipes/securitycraft/reinforced_light_gray_stained_glass_pane_from_dye": {
    "criteria": {
      "has_glass": "2025-01-10 14:12:36 -0300"
    },
    "done": true
  },
  "securitycraft:recipes/securitycraft/reinforced_brown_stained_glass": {
    "criteria": {
      "has_glass": "2025-01-10 14:12:36 -0300"
    },
    "done": true
  },
  "minecraft:recipes/redstone/repeater": {
    "criteria": {
      "has_redstone_torch": "2025-01-09 20:06:59 -0300"
    },
    "done": true
  },
  "minecraft:adventure/kill_a_mob": {
    "criteria": {
      "minecraft:skeleton": "2025-01-08 19:55:31 -0300"
    },
    "done": true
  },
  "securitycraft:recipes/securitycraft/secret_acacia_sign_item": {
    "criteria": {
      "has_sign": "2025-01-09 20:09:00 -0300"
    },
    "done": true
  },
  "securitycraft:recipes/securitycraft/reinforced_orange_stained_glass_pane_from_dye": {
    "criteria": {
      "has_glass": "2025-01-10 14:12:36 -0300"
    },
    "done": true
  },
  "ae2wtlib:recipes/wireless_universal_terminal/upgrade_pattern_encoding": {
    "criteria": {
      "has_wpt": "2025-01-08 19:15:19 -0300"
    },
    "done": true
  },
  "create:recipes/create.palettes/tiled_glass_from_glass_colorless_stonecutting": {
    "criteria": {
      "has_glass_colorless": "2025-01-10 14:12:36 -0300"
    },
    "done": true
  },
  "securitycraft:recipes/securitycraft/reinforced_magenta_stained_glass": {
    "criteria": {
      "has_glass": "2025-01-10 14:12:36 -0300"
    },
    "done": true
  },
  "bigreactors:recipes/bigreactors.reactor/reactor/reinforced/activetap_fe": {
    "criteria": {
      "has_item2": "2025-01-09 20:07:25 -0300"
    },
    "done": true
  },
  "minecraft:recipes/decorations/blue_carpet_from_white_carpet": {
    "criteria": {
      "has_white_carpet": "2025-01-09 19:57:08 -0300"
    },
    "done": true
  },
  "minecraft:recipes/building_blocks/stone": {
    "criteria": {
      "has_cobblestone": "2025-01-09 20:08:46 -0300"
    },
    "done": true
  },
  "moguns:weapons/root": {
    "criteria": {
      "tick": "2025-01-08 19:15:24 -0300"
    },
    "done": true
  },
  "create:crushing_wheel": {
    "criteria": {
      "0": "2025-01-09 20:05:20 -0300"
    },
    "done": true
  },
  "securitycraft:recipes/securitycraft/reinforced_pink_stained_glass": {
    "criteria": {
      "has_glass": "2025-01-10 14:12:36 -0300"
    },
    "done": true
  },
  "bigreactors:recipes/bigreactors.reactor/reactor/reinforced/activefluidport_forge": {
    "criteria": {
      "has_item2": "2025-01-09 20:09:09 -0300"
    },
    "done": true
  },
  "minecraft:adventure/adventuring_time": {
    "criteria": {
      "minecraft:snowy_slopes": "2025-01-09 19:08:39 -0300",
      "minecraft:sunflower_plains": "2025-01-09 19:08:35 -0300",
      "minecraft:river": "2025-01-09 19:08:33 -0300",
      "minecraft:dripstone_caves": "2025-01-09 19:15:43 -0300",
      "minecraft:flower_forest": "2025-01-09 19:06:39 -0300",
      "minecraft:frozen_peaks": "2025-01-09 19:11:41 -0300",
      "minecraft:meadow": "2025-01-08 19:15:19 -0300"
    },
    "done": false
  },
  "immersiveengineering:recipes/immersiveengineering/crafting/capacitor_hv": {
    "criteria": {
      "has_nickel_ingot": "2025-01-09 19:12:41 -0300"
    },
    "done": true
  },
  "securitycraft:recipes/securitycraft/reinforced_purple_stained_glass": {
    "criteria": {
      "has_glass": "2025-01-10 14:12:36 -0300"
    },
    "done": true
  },
  "ae2wtlib:recipes/wireless_universal_terminal/ce": {
    "criteria": {
      "has_wpt": "2025-01-08 19:15:19 -0300",
      "has_wct": "2025-01-08 19:15:19 -0300"
    },
    "done": true
  },
  "bigreactors:recipes/bigreactors.general/fluidizer/solidinjector": {
    "criteria": {
      "has_item2": "2025-01-08 19:50:11 -0300"
    },
    "done": true
  },
  "chiselsandbits:recipes/chiselsandbits/magnifying_glass": {
    "criteria": {
      "has_c": "2025-01-08 20:01:41 -0300"
    },
    "done": true
  },
  "projecte:recipes/projecte/iron_band": {
    "criteria": {
      "has_lava": "2025-01-09 20:09:09 -0300"
    },
    "done": true
  },
  "minecraft:recipes/combat/stone_sword": {
    "criteria": {
      "has_cobblestone": "2025-01-09 20:08:46 -0300"
    },
    "done": true
  },
  "minecraft:recipes/building_blocks/snow_block": {
    "criteria": {
      "has_snowball": "2025-01-08 19:18:09 -0300"
    },
    "done": true
  },
  "minecraft:recipes/decorations/cobblestone_wall": {
    "criteria": {
      "has_cobblestone": "2025-01-09 20:08:46 -0300"
    },
    "done": true
  },
  "minecraft:recipes/tools/stone_pickaxe": {
    "criteria": {
      "has_cobblestone": "2025-01-09 20:08:46 -0300"
    },
    "done": true
  },
  "securitycraft:recipes/securitycraft/reinforced_pink_stained_glass_pane_from_dye": {
    "criteria": {
      "has_glass": "2025-01-10 14:12:36 -0300"
    },
    "done": true
  },
  "ae2wtlib:recipes/wireless_universal_terminal/ca": {
    "criteria": {
      "has_wit": "2025-01-08 19:15:19 -0300",
      "has_wct": "2025-01-08 19:15:19 -0300"
    },
    "done": true
  },
  "minecraft:recipes/building_blocks/brown_stained_glass": {
    "criteria": {
      "has_glass": "2025-01-10 14:12:36 -0300"
    },
    "done": true
  },
  "securitycraft:recipes/securitycraft/reinforced_lime_stained_glass_pane_from_dye": {
    "criteria": {
      "has_glass": "2025-01-10 14:12:36 -0300"
    },
    "done": true
  },
  "ironfurnaces:coal": {
    "criteria": {
      "rainbowcoal": "2025-01-08 19:15:19 -0300"
    },
    "done": true
  },
  "minecraft:recipes/transportation/jungle_boat": {
    "criteria": {
      "in_water": "2025-01-09 19:15:51 -0300"
    },
    "done": true
  },
  "minecraft:adventure/shoot_arrow": {
    "criteria": {
      "shot_arrow": "2025-01-08 19:18:11 -0300"
    },
    "done": true
  },
  "minecraft:recipes/misc/netherite_ingot": {
    "criteria": {
      "has_netherite_scrap": "2025-01-08 19:50:11 -0300"
    },
    "done": true
  },
  "minecraft:recipes/decorations/cobblestone_wall_from_cobblestone_stonecutting": {
    "criteria": {
      "has_cobblestone": "2025-01-09 20:08:46 -0300"
    },
    "done": true
  },
  "travelersbackpack:recipes/travelersbackpack/enderman": {
    "criteria": {
      "has_ender_pearl": "2025-01-08 19:50:11 -0300"
    },
    "done": true
  },
  "securitycraft:recipes/securitycraft/reinforced_magenta_stained_glass_pane_from_dye": {
    "criteria": {
      "has_glass": "2025-01-10 14:12:36 -0300"
    },
    "done": true
  },
  "minecraft:recipes/building_blocks/light_gray_stained_glass": {
    "criteria": {
      "has_glass": "2025-01-10 14:12:36 -0300"
    },
    "done": true
  },
  "minecraft:recipes/transportation/dark_oak_boat": {
    "criteria": {
      "in_water": "2025-01-09 19:15:51 -0300"
    },
    "done": true
  },
  "securitycraft:recipes/securitycraft/reinforced_white_stained_glass": {
    "criteria": {
      "has_glass": "2025-01-10 14:12:36 -0300"
    },
    "done": true
  },
  "industrialforegoing:recipes/industrialforegoing_core/dryrubber": {
    "criteria": {
      "has_item": "2025-01-08 19:15:19 -0300"
    },
    "done": true
  },
  "securitycraft:recipes/securitycraft/secret_birch_sign_item": {
    "criteria": {
      "has_sign": "2025-01-09 20:09:00 -0300"
    },
    "done": true
  },
  "securitycraft:recipes/securitycraft/reinforced_pink_stained_glass_pane_from_glass": {
    "criteria": {
      "has_glass": "2025-01-10 14:12:36 -0300"
    },
    "done": true
  },
  "minecraft:recipes/decorations/yellow_carpet_from_white_carpet": {
    "criteria": {
      "has_white_carpet": "2025-01-09 19:57:08 -0300"
    },
    "done": true
  },
  "create:recipes/create.base/crafting/kinetics/vertical_gearboxfrom_conversion": {
    "criteria": {
      "has_item": "2025-01-09 20:04:42 -0300"
    },
    "done": true
  },
  "securitycraft:recipes/securitycraft/reinforced_lime_stained_glass_pane_from_glass": {
    "criteria": {
      "has_glass": "2025-01-10 14:12:36 -0300"
    },
    "done": true
  },
  "minecraft:recipes/decorations/gray_carpet_from_white_carpet": {
    "criteria": {
      "has_white_carpet": "2025-01-09 19:57:08 -0300"
    },
    "done": true
  },
  "minecraft:recipes/decorations/pink_carpet_from_white_carpet": {
    "criteria": {
      "has_white_carpet": "2025-01-09 19:57:08 -0300"
    },
    "done": true
  },
  "minecraft:recipes/tools/stone_axe": {
    "criteria": {
      "has_cobblestone": "2025-01-09 20:08:46 -0300"
    },
    "done": true
  },
  "securitycraft:recipes/securitycraft/secret_sign_item": {
    "criteria": {
      "has_sign": "2025-01-09 20:09:00 -0300"
    },
    "done": true
  },
  "securitycraft:recipes/securitycraft/reinforced_cyan_stained_glass_pane_from_glass": {
    "criteria": {
      "has_glass": "2025-01-10 14:12:36 -0300"
    },
    "done": true
  },
  "ae2wtlib:recipes/wireless_pattern_encoding_terminal": {
    "criteria": {
      "has_wt": "2025-01-08 19:15:19 -0300"
    },
    "done": true
  },
  "vanillatweaks:storage_blocks": {
    "criteria": {
      "has_sugar": "2025-01-08 19:15:19 -0300",
      "has_flint": "2025-01-08 19:15:19 -0300",
      "has_charcoal": "2025-01-08 19:15:19 -0300"
    },
    "done": true
  },
  "minecraft:recipes/building_blocks/pink_stained_glass": {
    "criteria": {
      "has_glass": "2025-01-10 14:12:36 -0300"
    },
    "done": true
  },
  "DataVersion": 2975
}